LICENSE.txt
MANIFEST.in
README.rst
pyproject.toml
setup.py
PyHEADTAIL/__init__.py
PyHEADTAIL/_version.py
PyHEADTAIL.egg-info/PKG-INFO
PyHEADTAIL.egg-info/SOURCES.txt
PyHEADTAIL.egg-info/dependency_links.txt
PyHEADTAIL.egg-info/requires.txt
PyHEADTAIL.egg-info/top_level.txt
PyHEADTAIL/aperture/__init__.py
PyHEADTAIL/aperture/aperture.py
PyHEADTAIL/cobra_functions/__init__.py
PyHEADTAIL/cobra_functions/curve_tools.py
PyHEADTAIL/cobra_functions/pdf_integrators_2d.py
PyHEADTAIL/cobra_functions/stats.c
PyHEADTAIL/cobra_functions/stats.pyx
PyHEADTAIL/feedback/__init__.py
PyHEADTAIL/feedback/transverse_damper.py
PyHEADTAIL/field_maps/Transverse_Efield_map.py
PyHEADTAIL/field_maps/__init__.py
PyHEADTAIL/field_maps/field_map.py
PyHEADTAIL/general/__init__.py
PyHEADTAIL/general/contextmanager.py
PyHEADTAIL/general/decorators.py
PyHEADTAIL/general/element.py
PyHEADTAIL/general/errfff.f90
PyHEADTAIL/general/pmath.py
PyHEADTAIL/general/printers.py
PyHEADTAIL/general/utils.py
PyHEADTAIL/gpu/__init__.py
PyHEADTAIL/gpu/gpu_utils.py
PyHEADTAIL/gpu/gpu_wrap.py
PyHEADTAIL/gpu/oldinit.py
PyHEADTAIL/gpu/particles.py
PyHEADTAIL/gpu/pypic.py
PyHEADTAIL/gpu/slicing.py
PyHEADTAIL/gpu/smoothing_kernels.cu
PyHEADTAIL/gpu/stats.cu
PyHEADTAIL/gpu/thrust_code.cu
PyHEADTAIL/gpu/thrust_interface.py
PyHEADTAIL/gpu/wofz.cu
PyHEADTAIL/gpu/wrapper.py
PyHEADTAIL/impedances/__init__.py
PyHEADTAIL/impedances/wake_kicks.py
PyHEADTAIL/impedances/wakes.py
PyHEADTAIL/machines/__init__.py
PyHEADTAIL/machines/synchrotron.py
PyHEADTAIL/monitors/__init__.py
PyHEADTAIL/monitors/monitors.py
PyHEADTAIL/multipoles/__init__.py
PyHEADTAIL/multipoles/multipoles.py
PyHEADTAIL/particles/__init__.py
PyHEADTAIL/particles/generators.py
PyHEADTAIL/particles/particles.py
PyHEADTAIL/particles/rfbucket_matching.py
PyHEADTAIL/particles/slicing.py
PyHEADTAIL/radiation/__init__.py
PyHEADTAIL/radiation/radiation.py
PyHEADTAIL/rfq/__init__.py
PyHEADTAIL/rfq/rfq.py
PyHEADTAIL/spacecharge/__init__.py
PyHEADTAIL/spacecharge/pypic_factory.py
PyHEADTAIL/spacecharge/pypic_spacecharge.py
PyHEADTAIL/spacecharge/spacecharge.py
PyHEADTAIL/spacecharge/transverse_spacecharge.py
PyHEADTAIL/trackers/__init__.py
