Metadata-Version: 2.1
Name: PyHEADTAIL
Version: 1.16.5
Summary: CERN PyHEADTAIL numerical n-body simulation code for simulating macro-particle beam dynamics with collective effects.
Home-page: https://github.com/PyCOMPLETE/PyHEADTAIL
Author: Kevin Li
Author-email: Kevin.Shing.Bruce.Li@cern.ch
Maintainer: Adrian Oeftiger
Maintainer-email: Adrian.Oeftiger@cern.ch
License-File: LICENSE.txt
Requires-Dist: h5py
Requires-Dist: numpy
Requires-Dist: scipy
